{
  "adenoid cystic carcinoma": "DOID:8618 / oral cavity cancer",
  "adrenocortical": "DOID:3953 / adrenal gland cancer",
  "ampullary": "DOID:1793 / pancreatic cancer",
  "appendiceal": "DOID:11239 / appendix cancer",
  "astrocytoma": "DOID:4706 / brain cancer",
  "basal cell": "DOID:4159 / skin cancer",
  "b-cell": "DOID:2531 / hematologic cancer",
  "bladder/urinary": "DOID:11054 / urinary bladder cancer",
  "bowel": "DOID:9256 / colorectal cancer",
  "breast": "DOID:1612 / breast cancer",
  "cervical": "DOID:4362 / cervical cancer",
  "cholangiocarcinoma": "DOID:4606 / bile duct cancer",
  "cns/brain": "DOID:1319 / brain cancer",
  "colon": "DOID:9256 / colorectal cancer",
  "colorectal": "DOID:9256 / colorectal cancer",
  "cutaneous": "DOID:4159 / skin cancer",
  "desmoplastic": "DOID:4159 / skin cancer",
  "endometrial": "DOID:363 / uterine cancer",
  "esophageal": "DOID:5041 / esophageal cancer",
  "esophagogastric": "DOID:5041 / esophageal cancer & DOID:10534 / stomach cancer",
  "esophagus/stomach": "DOID:5041 / esophageal cancer & DOID:10534 / stomach cancer",
  "ewing": "DOID:184 / bone cancer",
  "gallbladder": "DOID:3121 / gallbladder cancer",
  "glioblastoma": "DOID:1319 / brain cancer",
  "glioma": "DOID:1319 / brain cancer",
  "head": "DOID:11934 / head and neck cancer",
  "hepatocellular": "DOID:3571 / liver cancer",
  "histiocytic": "DOID:0060073 / lymphatic system cancer",
  "leukemia": "DOID:2531 / hematologic cancer",
  "leukemia/lymphoma": "DOID:2531 / hematologic cancer",
  "lung": "DOID:1324 / lung cancer",
  "lymphoid": "DOID:2531 / hematologic cancer",
  "lymphoma": "DOID:2531 / hematologic cancer",
  "mature t and nk neoplasms": "DOID:2531 / hematologic cancer",
  "meningioma": "DOID:3565 / meningioma",
  "myelodysplastic": "DOID:2531 / hematologic cancer",
  "myeloid": "DOID:2531 / hematologic cancer",
  "myeloma": "DOID:2531 / hematologic cancer",
  "myeloproliferative": "DOID:2531 / hematologic cancer",
  "nasopharyngeal": "DOID:10811 / nasal cavity cancer & DOID:0060119 / pharynx cancer",
  "neuroepithelial": "DOID:1319 / brain cancer",
  "non-seminomatous": "DOID:2998 / testicular cancer",
  "ovarian": "DOID:2394 / ovarian cancer",
  "ovary": "DOID:2394 / ovarian cancer",
  "ovary/fallopian": "DOID:1964 / fallopian tube cancer & DOID:2394 / ovarian cancer",
  "pancreas": "DOID:1793 / pancreatic cancer",
  "pancreatic": "DOID:1793 / pancreatic cancer",
  "pituitary": "DOID:1785 / pituitary cancer",
  "pleural": "DOID:5158 / pleural cancer",
  "primary dlbcl of the central nervous system": "DOID:2531 / hematologic cancer",
  "prostate": "DOID:10283 / prostate cancer",
  "rectal": "DOID:9256 / colorectal cancer",
  "renal":  "DOID:263 / kidney cancer",
  "retinoblastoma": "DOID:2174 / ocular cancer",
  "rhabdoid": "DOID:263 / kidney cancer",
  "sheath": "DOID:1192 / peripheral nervous system neoplasm",
  "stomach": "DOID:10534 / stomach cancer",
  "thymic": "DOID:3277 / thymus cancer",
  "thymoma": "DOID:3277 / thymus cancer",
  "thyroid": "DOID:1781 / thyroid cancer",
  "urinary": "DOID:11054 / urinary bladder cancer",
  "urothelial": "DOID:11054 / urinary bladder cancer",
  "uterine": "DOID:363 / uterine cancer",
  "uveal": "DOID:2174 / ocular cancer",
  "vulva/vagina": "DOID:119 / vaginal cancer & DOID:1245 / vulva cancer"
}